dtalarm/__init__.py
dtalarm/base.py
dtalarm/client.py
dtalarm/config.py
dtalarm-1.1.0.dist-info/LICENSE
dtalarm-1.1.0.dist-info/METADATA
dtalarm-1.1.0.dist-info/WHEEL
dtalarm-1.1.0.dist-info/top_level.txt
dtalarm-1.1.0.dist-info/RECORD
