Metadata-Version: 2.1
Name: dtalarm
Version: 1.1.0
Summary: Python integration with DRIVE
Home-page: UNKNOWN
Author: TimeAshore
Author-email: timeashore@163.com
License: UNKNOWN
Platform: UNKNOWN
Classifier: Programming Language :: Python :: 3
Classifier: Programming Language :: Python :: 3.6
Classifier: Programming Language :: Python :: 3.7
Classifier: Programming Language :: Python :: 3.8
Classifier: Programming Language :: Python :: 3.9
Classifier: License :: OSI Approved :: MIT License
Classifier: Operating System :: OS Independent
Requires-Python: >=3.6.8
License-File: LICENSE
Requires-Dist: Pillow
Requires-Dist: requests
Requires-Dist: kaleido (>=0.2.1)
Requires-Dist: plotly
Requires-Dist: numpy
Requires-Dist: pandas
